poorajenny2/__init__.py
poorajenny2/poora.py
PooraJenny2-0.2.dist-info/METADATA
PooraJenny2-0.2.dist-info/WHEEL
PooraJenny2-0.2.dist-info/top_level.txt
PooraJenny2-0.2.dist-info/RECORD
