Metadata-Version: 2.1
Name: PooraJenny2
Version: 0.2
Summary: Poorra apuestas
Home-page: https://gitlab.com/jennylicini/poorajenny.git
Author: Jenny Licini
Author-email: y5762434m@iespoblenou.org
License: MIT
Platform: UNKNOWN
Classifier: Programming Language :: Python :: 3
Classifier: License :: OSI Approved :: MIT License
Classifier: Operating System :: OS Independent
